<Language Name="Lietuvių" IsDefault="false" IsRightToLeft="false">
  <LocaleResource Name="AdminEmail">
    <Value>Administratoriaus el. paštas</Value>
  </LocaleResource>
  <LocaleResource Name="AdminEmailRequired">
    <Value>Įveskite el. pašta</Value>
  </LocaleResource>
  <LocaleResource Name="AdminPassword">
    <Value>Administratoriaus slaptažodis</Value>
  </LocaleResource>
  <LocaleResource Name="AdminPasswordRequired">
    <Value>Įveskite slaptažodį</Value>
  </LocaleResource>
  <LocaleResource Name="ConfigureDirectoryPermissions">
    <Value>'{0}' Paskyra neaktyvuota modifikavimui papkėje '{1}'. Prašome sukonfigūruoti priėjimo teises.</Value>
  </LocaleResource>
  <LocaleResource Name="ConfigureFilePermissions">
    <Value>'{0}' Paskyra neaktyvuota modifikavimui papkėje '{1}'. Prašome sukonfigūruoti priėjimo teises.</Value>
  </LocaleResource>
  <LocaleResource Name="ConfirmPassword">
    <Value>Patvirtinkite slaptažodį</Value>
  </LocaleResource>
  <LocaleResource Name="ConfirmPasswordRequired">
    <Value>Patvirtinkite slaptažodį</Value>
  </LocaleResource>
  <LocaleResource Name="ConnectionString">
    <Value>Prisijungimo informacija</Value>
  </LocaleResource>
  <LocaleResource Name="ConnectionStringRequired">
    <Value>MongoDB Įveskite prisijungimo informacija</Value>
  </LocaleResource>
  <LocaleResource Name="ConnectionStringValues">
    <Value>Įveskite MongoDB prisijungimo duomenis</Value>
  </LocaleResource>
  <LocaleResource Name="ConnectionStringWrongFormat">
    <Value>Klaidingas MongoDB prisijungimo duomenų formatas</Value>
  </LocaleResource>
  <LocaleResource Name="CreateDatabaseIfDoesNotExist">
    <Value>Sukurti duomenų baze jeigu nėra atitikmens.</Value>
  </LocaleResource>
  <LocaleResource Name="CreateSampleData">
    <Value>Įdiegti pavyzdinius duomenis?</Value>
  </LocaleResource>
  <LocaleResource Name="CustomCollation">
    <Value>Norodykite modifikuotus MongoDB Serverio duomenis</Value>
  </LocaleResource>
  <LocaleResource Name="DatabaseCreationError">
    <Value>Klaida kuriant duomenu baze: {0}</Value>
  </LocaleResource>
  <LocaleResource Name="DatabaseInformation">
    <Value>Duomenų bazės informacija</Value>
  </LocaleResource>
  <LocaleResource Name="DatabaseName">
    <Value>Duomenų bazės pavadinimas</Value>
  </LocaleResource>
  <LocaleResource Name="DatabaseNameRequired">
    <Value>Įveskite duomenų bazės pavadinima</Value>
  </LocaleResource>
  <LocaleResource Name="DatabaseNotExists">
    <Value>Tokios duomenų bazės nėra, arba jus neturite teisės prie jos prisijungti.</Value>
  </LocaleResource>
  <LocaleResource Name="DataProviderRequired">
    <Value>Pasirinkite duomenų teikėją</Value>
  </LocaleResource>
  <LocaleResource Name="Documentation1">
    <Value>Jeigu reikia daugiau informacijos kaip naudotis grandnode, perskaitykite</Value>
  </LocaleResource>
  <LocaleResource Name="Documentation2">
    <Value>dokumentacija grandnode.com svetainėje</Value>
  </LocaleResource>
  <LocaleResource Name="Example">
    <Value>Pavyzdys</Value>
  </LocaleResource>
  <LocaleResource Name="Install">
    <Value>Įdiegti</Value>
  </LocaleResource>
  <LocaleResource Name="Installing">
    <Value>Diegiama grandnode aplikacija...</Value>
  </LocaleResource>
  <LocaleResource Name="PasswordsDoNotMatch">
    <Value>Slaptažodžiai nesutampa</Value>
  </LocaleResource>
  <LocaleResource Name="RawConnectionString">
    <Value>Įveskite prisijungimo duomenis vienoje eilutėje</Value>
  </LocaleResource>
  <LocaleResource Name="Recommended">
    <Value>[Rekomenduojama]</Value>
  </LocaleResource>
  <LocaleResource Name="RestartInstallation">
    <Value>Perkrauti diegima</Value>
  </LocaleResource>
  <LocaleResource Name="RestartInstallationTooltip">
    <Value>Paspauskite norėdami perkrauti diegimo procesą (ištrinti visas patalpintas reikšmes)</Value>
  </LocaleResource>
  <LocaleResource Name="SetupFailed">
    <Value>Diegimo klaida: {0}</Value>
  </LocaleResource>
  <LocaleResource Name="MongoDBAuthentication">
    <Value>Naudoti MongoDB Serverio paskyrą</Value>
  </LocaleResource>
  <LocaleResource Name="MongoDBCompact">
    <Value>Naudoti standartine duomenų talpykla (MongoDB Server Compact)</Value>
  </LocaleResource>
  <LocaleResource Name="MongoDBServerName">
    <Value>MongoDB Serverio pavadinimas</Value>
  </LocaleResource>
  <LocaleResource Name="MongoDBServerNameRequired">
    <Value>Įveskite MongoDB serverio pavadinimą</Value>
  </LocaleResource>
  <LocaleResource Name="MongoDBServerPassword">
    <Value>MongoDB Slaptažodis</Value>
  </LocaleResource>
  <LocaleResource Name="MongoDBServerPasswordRequired">
    <Value>Įveskite MongoDB slaptažodį</Value>
  </LocaleResource>
  <LocaleResource Name="MongoDBServerUsername">
    <Value>MongoDB Vartotojo vardas</Value>
  </LocaleResource>
  <LocaleResource Name="MongoDBServerUsernameRequired">
    <Value>Įveskite MongoDB vartotojo vardą</Value>
  </LocaleResource>
  <LocaleResource Name="MongoDBStandard">
    <Value>Naudoti MongoDB Serverio (arba MongoDB Express) duomenų bazę?</Value>
  </LocaleResource>
  <LocaleResource Name="StoreInformation">
    <Value>E-parduotuvės informacija</Value>
  </LocaleResource>
  <LocaleResource Name="Title">
    <Value>grandnode diegimas</Value>
  </LocaleResource>
  <LocaleResource Name="Tooltip1">
    <Value>grandnode yra labiausiai paplitusi ASP.NET elektroninės prekybos sistema. Šis vedlys pedės jums įdiegti bei sukonfiguruoti grandnode sistemą.</Value>
  </LocaleResource>
  <LocaleResource Name="Tooltip2">
    <Value>Norėdami įdiegti šią aplikaciją, jūs turite žinoti šiek tiek informacijos apie savo MongoDB serverį (prisijugimo informaciją). Prašome susisiekti su savo ISP, jei būtina. Jeigu diegiate į vietinį kompiuterį ar serverį, jums gali prireikti informacijos iš jūsų sistemos administratoriaus.</Value>
  </LocaleResource>
  <LocaleResource Name="WindowsAuthentication">
    <Value>Naudoti integruotą Windows autentifikavimą</Value>
  </LocaleResource>
</Language>